pyPTF/__init__.py
pyPTF/fkmeans.py
pyPTF/optim.py
pyPTF/ptf.py
pyPTF/symb_functions.py
pyPTF/utils.py
pyPTF/datasets/__init__.py
pyPTF/datasets/base.py
pyPTF/datasets/water.py
pyPTF/datasets/data/water.csv
test/__init__.py
test/test_datasets.py
test/test_fkmeans.py
test/test_ptf.py
pyPTF-0.1.0.dist-info/LICENSE
pyPTF-0.1.0.dist-info/METADATA
pyPTF-0.1.0.dist-info/WHEEL
pyPTF-0.1.0.dist-info/top_level.txt
pyPTF-0.1.0.dist-info/RECORD
