Metadata-Version: 2.1
Name: pyPTF
Version: 0.1.0
Summary: Pedotransfer function development using Genetic Programming
Home-page: https://github.com/spadarian/pyPTF
Author: José Padarian
Author-email: spadarian@gmail.com
License: GPL-3.0
Keywords: soil modelling uncertainty
Platform: UNKNOWN
Classifier: Development Status :: 3 - Alpha
Classifier: Intended Audience :: Science/Research
Classifier: Intended Audience :: Education
Classifier: Intended Audience :: Developers
Classifier: License :: OSI Approved
Classifier: Topic :: Software Development
Classifier: Topic :: Scientific/Engineering
Classifier: Operating System :: Unix
Classifier: Operating System :: MacOS
Classifier: Programming Language :: Python
Classifier: Programming Language :: Python :: 3
Classifier: Programming Language :: Python :: 3.4
Classifier: Programming Language :: Python :: 3.5
Classifier: Programming Language :: Python :: 3.6
Requires-Dist: gplearn (==0.3.0)
Requires-Dist: sympy (==1.2)
Requires-Dist: pygmo (>=2.8)
Requires-Dist: pandas (>=0.22)
Requires-Dist: matplotlib (==2.2.3)
Provides-Extra: docs
Requires-Dist: Sphinx; extra == 'docs'
